setup.py
agar/__init__.py
agar/_version.py
agar/auth.py
agar/config.py
agar/counter.py
agar/dates.py
agar/env.py
agar/image.py
agar/json.py
agar/keygen.py
agar/models.py
agar/sessions.py
agar/url.py
agar.egg-info/PKG-INFO
agar.egg-info/SOURCES.txt
agar.egg-info/dependency_links.txt
agar.egg-info/not-zip-safe
agar.egg-info/top_level.txt
agar/django/__init__.py
agar/django/decorators.py
agar/django/forms.py
agar/django/templates.py
agar/templatetags/__init__.py
agar/templatetags/webapp2.py
agar/test/__init__.py
agar/test/base_test.py
agar/test/mock_urlfetch_test.py
agar/test/web_test.py