Metadata-Version: 1.0
Name: agar
Version: 0.5.1
Summary: A collection of libraries for making Google App Engine development easier.
Home-page: http://bitbucket.org/gumptioncom/agar
Author: Thomas Bombach, Jr.
Author-email: thomas@gumption.com
License: MIT
Platform: UNKNOWN
Classifier: Development Status :: 3 - Alpha
Classifier: Environment :: Web Environment
Classifier: Intended Audience :: Developers
Classifier: Topic :: Internet :: WWW/HTTP
Classifier: Topic :: Utilities
Classifier: License :: OSI Approved :: MIT License
